MANIFEST.in
setup.py
docs/genindex.html
docs/getting_started.html
docs/index.html
docs/install.html
docs/intro.html
docs/modules.html
docs/objects.inv
docs/overview.html
docs/py-modindex.html
docs/quick_start.html
docs/search.html
docs/searchindex.js
docs/toyz.html
docs/toyz.utils.db_interfaces.html
docs/toyz.utils.html
docs/toyz.web.html
docs/toyz_logo.png
docs/_sources/index.txt
docs/_static/css/badge_only.css
docs/_static/css/theme.css
docs/_static/fonts/fontawesome-webfont.eot
docs/_static/fonts/fontawesome-webfont.svg
docs/_static/fonts/fontawesome-webfont.ttf
docs/_static/fonts/fontawesome-webfont.woff
docs/_static/images/group_settings.png
docs/_static/images/open_file.png
docs/_static/images/plots.png
docs/_static/images/user_settings.png
docs/_static/js/theme.js
docs/source/conf.py
docs/source/contributing.rst
docs/source/custom_toyz.rst
docs/source/getting_started.rst
docs/source/highcharts.rst
docs/source/index.rst
docs/source/install.rst
docs/source/modules.rst
docs/source/overview.rst
docs/source/toyz.rst
docs/source/toyz.utils.db_interfaces.rst
docs/source/toyz.utils.rst
docs/source/toyz.web.rst
docs/source/toyz_api.rst
docs/source/viewer.rst
docs/source/web_gui.rst
docs/source/workspaces.rst
scripts/README.rst
scripts/toyz
toyz/__init__.py
toyz/__init__.pyc
toyz/bugs.txt
toyz/version.py
toyz/version.pyc
toyz.egg-info/PKG-INFO
toyz.egg-info/SOURCES.txt
toyz.egg-info/dependency_links.txt
toyz.egg-info/not-zip-safe
toyz.egg-info/requires.txt
toyz.egg-info/top_level.txt
toyz/third_party/graph3d/graph3d-1.2/CHANGELOG
toyz/third_party/graph3d/graph3d-1.2/LICENSE
toyz/third_party/graph3d/graph3d-1.2/NOTICE
toyz/third_party/graph3d/graph3d-1.2/README
toyz/third_party/graph3d/graph3d-1.2/graph3d-min.js
toyz/third_party/graph3d/graph3d-1.2/graph3d.js
toyz/third_party/graph3d/graph3d-1.2/doc/default.css
toyz/third_party/graph3d/graph3d-1.2/doc/example.html
toyz/third_party/graph3d/graph3d-1.2/doc/graph3d.png
toyz/third_party/graph3d/graph3d-1.2/doc/graph3d120x60.png
toyz/third_party/graph3d/graph3d-1.2/doc/index.html
toyz/third_party/graph3d/graph3d-1.2/doc/jsdoc/files.html
