Metadata-Version: 1.0
Name: toyz
Version: 0.1.1
Summary: Data reduction and analysis software
Home-page: http://fred3m.github.io/toyz/
Author: Fred Moolekamp
Author-email: fred.moolekamp@gmail.com
License: BSD 3-clause
Platform: UNKNOWN
